{
  "goid": "bd1e20c71253a47ac5b4ef1ddeef5bc0",
  "name": "172594b6-18ba-4b0c-8d61-807db457e81d",
  "checksum": "7fa07814b071fb28cc9d49d14da85ba5c9f8bbd5",
  "enabled": true,
  "entityClassName": "com.l7tech.external.assertions.apiportalintegration.server.PortalManagedEncass",
  "valueXml": "<?xml version=\"1.0\" encoding=\"UTF-8\"?>\n<java version=\"17.0.10\" class=\"java.beans.XMLDecoder\">\n <object class=\"com.l7tech.external.assertions.apiportalintegration.server.PortalManagedEncass\" id=\"PortalManagedEncass0\">\n  <void property=\"encassGuid\">\n   <string>172594b6-18ba-4b0c-8d61-807db457e81d</string>\n  </void>\n  <void property=\"encassId\">\n   <string>4c5453d9a34fa56f13df266ac9483439</string>\n  </void>\n  <void id=\"Boolean0\" method=\"isEnabled\"/>\n  <void property=\"hasRouting\">\n   <object idref=\"Boolean0\"/>\n  </void>\n  <void property=\"id\">\n   <string>bd1e20c71253a47ac5b4ef1ddeef5bc0</string>\n  </void>\n  <void property=\"valueXml\">\n   <string></string>\n  </void>\n  <void property=\"version\">\n   <int>5</int>\n  </void>\n </object>\n</java>\n"
}