{
  "goid": "51b41dca9eec541b35ae23d02d0e1577",
  "guid": "1d682484-d9d7-47f7-9671-9ae9e10f5af4",
  "name": "Portal Read Hashed Metadata",
  "checksum": "325404efa762752578c67bbc2b0ffb1b4f1fc1bd",
  "description": "Read Hashed Metadata",
  "policyName": "Portal Read Hashed Metadata",
  "encassArgs": [
    {
      "name": "hashing_metadata",
      "type": "STRING",
      "ordinal": 1,
      "guiPrompt": false
    }
  ],
  "encassResults": [
    {
      "name": "algorithm.result",
      "type": "STRING"
    },
    {
      "name": "salt.result",
      "type": "STRING"
    }
  ],
  "properties": [
    {
      "name": "allowTracing",
      "value": "false"
    },
    {
      "name": "paletteFolder",
      "value": "customAssertions"
    },
    {
      "name": "passMetricsToParent",
      "value": "false"
    }
  ]
}